ls_converter/__init__.py
ls_converter/errors.py
ls_converter/meta.py
ls_converter/utils.py
ls_converter-0.0.1.dist-info/LICENSE
ls_converter-0.0.1.dist-info/WHEEL
ls_converter-0.0.1.dist-info/METADATA
ls_converter-0.0.1.dist-info/RECORD
