Metadata-Version: 2.1
Name: ls-converter
Version: 0.0.1
Summary: Creates ready-to-use Label Studio pre-populated JSON files from popular OCR formats.
Home-page: https://github.com/Living-with-machines/label-studio-converter
License: MIT
Keywords: computer-vision,deep-learning,image-annotation,annotation,annotations,dataset,image-classification,labeling,datasets,semantic-segmentation,annotation-tool,text-annotation,boundingbox,image-labeling,labeling-tool,image-labelling-tool,data-labeling,label-studio,ocr
Author: Kalle Westerling
Author-email: kalle.westerling@bl.uk
Requires-Python: >=3.7,<4.0
Classifier: Development Status :: 3 - Alpha
Classifier: Intended Audience :: Developers
Classifier: Intended Audience :: Science/Research
Classifier: License :: OSI Approved :: MIT License
Classifier: Operating System :: OS Independent
Classifier: Programming Language :: Python :: 3
Classifier: Programming Language :: Python :: 3.10
Classifier: Programming Language :: Python :: 3.7
Classifier: Programming Language :: Python :: 3.8
Classifier: Programming Language :: Python :: 3.9
Classifier: Topic :: Scientific/Engineering :: Image Processing
Classifier: Topic :: Text Processing
Classifier: Topic :: Utilities
Requires-Dist: Pillow (>=9.3.0,<10.0.0)
Requires-Dist: requests (>=2.28.1,<3.0.0)
Requires-Dist: xmltodict (>=0.13.0,<0.14.0)
Project-URL: Repository, https://github.com/Living-with-machines/label-studio-converter
